webdevaccess/__init__.py
webdevaccess/htmlElements/__init__.py
webdevaccess/htmlElements/__main__.py
webdevaccess/htmlElements/main.py
webdevaccess/htmlElements/mdnElements.py
webdevaccess-0.1.0.dist-info/entry_points.txt
webdevaccess-0.1.0.dist-info/LICENSE
webdevaccess-0.1.0.dist-info/METADATA
webdevaccess-0.1.0.dist-info/WHEEL
webdevaccess-0.1.0.dist-info/RECORD
